seminor-dir/riscv-np/np/riscv.vh
// filepath: /Users/motodakoutaroukari/Documents/workspace/github.com/KotaroMotoda/rv32i-pipeline-processor/seminor-dir/riscv-np/np/riscv.vh
`define IR_OP          IR[6:0]
`define IR_RS1         IR[19:15]
`define IR_RS2         IR[24:20]
`define IR_RD          IR[11:7]
`define IR_F3          IR[14:12]
`define IR_F7          IR[31:25]

`define OP_LUI         7'b0110111
`define OP_AUIPC       7'b0010111
`define OP_JAL         7'b1101111
`define OP_JALR        7'b1100111
`define OP_BR          7'b1100011
`define OP_LOAD        7'b0000011
`define OP_STORE       7'b0100011
`define OP_FUNC1       7'b0010011
`define OP_FUNC2       7'b0110011

`define FT_U           3'b000
`define FT_J           3'b001
`define FT_B           3'b010
`define FT_I           3'b011
`define FT_S           3'b100
`define FT_R           3'b101

`define IADD           5'b00000
`define ISUB           5'b00001
`define IAND           5'b00010
`define IOR            5'b00011
`define IXOR           5'b00100
`define ISLL           5'b00101
`define ISRL           5'b00110
`define ISRA           5'b00111
`define SLT            5'b01000
`define SLTU           5'b01001

`define IADD           5'b00000
`define ISUB           5'b00001
`define IAND           5'b00010
`define IOR            5'b00011
`define IXOR           5'b00100
`define ISLL           5'b00101
`define ISRL           5'b00110
`define ISRA           5'b00111
`define SLT            5'b01000
`define SLTU           5'b01001

`define BIG_ENDIAN
// Uncomment the line below for little-endian support
// `define LITTLE_ENDIAN

seminor-dir/riscv-np/np/alu.vh
// filepath: /Users/motodakoutaroukari/Documents/workspace/github.com/KotaroMotoda/rv32i-pipeline-processor/seminor-dir/riscv-np/np/alu.vh
`define IADD  5'b00000
`define ISUB  5'b00001
`define IAND  5'b00010
`define IOR   5'b00011
`define IXOR  5'b00100
`define ISLL  5'b00101
`define ISRL  5'b00110
`define ISRA  5'b00111
`define SLT   5'b01000
`define SLTU  5'b01001
`define IADD  5'b00000
`define IBEQ  5'b00010
`define IBNE  5'b00011
`define IBLT  5'b00100
`define IBLTU 5'b00101
`define IBGE  5'b00110
`define IBGEU 5'b00111
`define ILOAD 5'b01000
`define ISTORE 5'b01001
`define IAUIPC 5'b01010
`define IJAL  5'b01011
`define IJALR 5'b01100
`define OP_LOAD  7'b0000011
`define OP_STORE 7'b0100011
`define OP_LUI   7'b0110111
`define OP_AUIPC 7'b0010111
`define OP_JAL   7'b1101111
`define OP_JALR  7'b1100111
`define OP_BR    7'b1100011
`define OP_FUNC1 7'b0010011
`define OP_FUNC2 7'b0110011
`define FT_U     3'b00
`define FT_I     3'b01
`define FT_S     3'b10
`define FT_B     3'b11
`define FT_J     3'b100
`define IR_OP    IR[6:0]
`define IR_F3    IR[14:12]
`define IR_F7    IR[31:25]
`define IR_RS1   IR[19:15]
`define IR_RS2   IR[24:20]
`define IR_RD    IR[11:7]

seminor-dir/riscv-np/np/inst.vh
//
// Opecode field
//
`define IR_OP  	IR[ 6: 0]
`define IR_RD	IR[11: 7]
`define IR_F3	IR[14:12]
`define IR_RS1	IR[19:15]
`define IR_RS2	IR[24:20]
`define IR_F7	IR[31:25]
`define IR_ADD_OR_SUB	IR[30:27]
`define IR_PACK_SIZE	IR[26:25]


// opecode
`define OP_LUI		7'b0110111 
`define OP_AUIPC	7'b0010111 
`define OP_JAL		7'b1101111 
`define OP_JALR		7'b1100111 
`define OP_BR		7'b1100011 
`define OP_LOAD		7'b0000011 
`define OP_STORE	7'b0100011 
`define OP_FUNC1	7'b0010011 
`define OP_FUNC2	7'b0110011 
`define OP_FENCEX	7'b0001111 
`define OP_FUNC3	7'b1110011 
`define OP_PACK		7'b0111011

// Instruction Format Type ( 00: illegal instruction )
`define FT_R	3'b001
`define FT_I	3'b010
`define FT_S	3'b011
`define FT_U	3'b100
`define FT_J	3'b101
`define FT_B	3'b110
`define FT_P	3'b111

seminor-dir/riscv-np/np/alu.v
`include "alu.vh"
module alu ( A, B, C, Y );
    input [31:0] A;
    input [31:0] B;
    input [4:0] C;
    output [31:0] Y;
    reg [31:0] Y;

    reg [32:0] X; // 33bitで計算（オーバーフロー検出のため）

    wire overflowFlag; // overflow flag
    wire zeroFlag; // zero flag
    wire lessThanUnsignedFlag; // less than unsigned flag
    wire lessThanFlag; // less than flag


    always @( A or B or C )
        begin
            case( C )
                `ADD : X <= { 1'b0, A } + { 1'b0, B };
                `SUB : X <= { 1'b0, A } - { 1'b0, B };
                `IADD : X <= { 1'b0, A } + { 1'b0, B };
                `IAND : X <= { 1'b0, A } & { 1'b0, B };
                `IOR  : X <= { 1'b0, A } | { 1'b0, B };
                `IXOR : X <= { 1'b0, A } ^ { 1'b0, B };
                default: X <= { 1'b0, A } - { 1'b0, B };
            endcase
        end

    // Flags
    assign overflowFlag = ((A[31] & ~B[31] & ~X[31]) | (~A[31] & B[31] & X[31]));
    assign zeroFlag = (X[31:0] == 32'b0);                         
    assign lessThanUnsignedFlag = (A < B);                    
    assign lessThanFlag = ($signed(A) < $signed(B));      

    // Output MUX
    always @( overflowFlag or zeroFlag or lessThanUnsignedFlag or lessThanFlag or X or C )
        begin
            case( C )
                `lessThan             : Y <= {31'b0, lessThanFlag};
                `lessThanUnsigned     : Y <= {31'b0, lessThanUnsignedFlag};
                `greaterEqual         : Y <= {31'b0, ~lessThanFlag};
                `greaterEqualUnsigned : Y <= {31'b0, ~lessThanUnsignedFlag};
                `equal                : Y <= {31'b0, zeroFlag};
                `notEqual             : Y <= {31'b0, ~zeroFlag};
                default               : Y <= X[31:0];
            endcase
        end
endmodule

seminor-dir/riscv-np/np/rf.v
module rf( CLK, RNUM1, RNUM2, RDATA1, RDATA2, WNUM, WDATA );
   input         CLK;
   input   [4:0] RNUM1, RNUM2, WNUM;
   output reg [31:0] RDATA1, RDATA2;
   input  [31:0] WDATA;
   
   reg    [31:0] REGISTER_FILE[1:31];
   
   always @( posedge CLK )
     begin
	if( WNUM != 5'b00000 )
	  REGISTER_FILE[WNUM] <= WDATA;
     end

   always @( negedge CLK )
     begin
           RDATA1 <= (RNUM1 != 0) ? REGISTER_FILE[RNUM1] : 32'h0000_0000;
           RDATA2 <= (RNUM2 != 0) ? REGISTER_FILE[RNUM2] : 32'h0000_0000;
     end
      
endmodule // rf

seminor-dir/riscv-np/np/riscv_full.v
`include "riscv.vh"
`include "inst.vh"
`include "alu.vh"
`define LITTLE_ENDIAN

module riscv
    #(
        parameter IMEM_BASE = 32'h0000_0000,
        parameter IMEM_SIZE = 32768,	// 32kW = 128kB
        parameter IMEM_FILE = "prog.mif",
        parameter DMEM_BASE = 32'h0010_0000,
        parameter DMEM_SIZE = 32768,	// 32kW = 128kB
        parameter DMEM_FILE = "data.mif"
    )
    (
        input CLK,
        input RSTN,
        output reg [31:0] WE_RD_VAL
    );

    wire RST;
    assign RST = ~RSTN;

    // IM 
    reg [31:0] imem[0:IMEM_SIZE-1];

    initial
    begin
        $readmemh( IMEM_FILE, imem );
    end

    // IF reg
    reg [31:0] PC_IF;
    wire [31:0] PC4_IF;
    wire [31:0] IDATA_IF;

    // IF/ID pipeline reg
    reg [31:0] PC_FD;
    reg [31:0] IDATA_FD;
    reg [31:0] PC4_FD;

    // ID reg
    wire [31:0] IR;
    reg [4:0] IALU_ID;
    wire [31:0] RF_DATA1;
    wire [31:0] RF_DATA2;
    reg [4:0] RD_ID;
    reg [15:0] IMM_VAL_ID;
    reg [31:0] IMM_VAL_EXT_ID; // 符号拡張済みimm値
    reg [2:0] FT_ID; // 命令フォーマットタイプ
    
    // Control reg in ID
    reg [1:0] MemtoReg_ID;
    reg RegWrite_ID;
    reg [31:0] Branch_ID;
    reg [1:0] MemWrite_ID;
    reg [1:0] MemRead_ID;
    reg ALUSrc_ID;
    reg [1:0] ALUOp_ID;
    reg [1:0] ALUDst_ID;
    reg DMSE_ID; // 0: unsigned, 1: signed loadでしか用いない.
    reg ALUorSHIFT_ID; // 0: ALU, 1: SHIFT VAL_MUXの選択用
    reg RS1_PC_ID;
    reg RS1_Z_ID;
    reg PC_E_ID;

    // ID/EX pipeline reg
    reg [31:0] PC4_DE;
    reg [31:0] PC_DE;
    reg [31:0] RF_DATA1_DE;
    reg [31:0] RF_DATA2_DE;
    reg [4:0] IALU_DE;
    reg [31:0] IMM_VAL_DE;
    reg [4:0] RD_DE;
    // Control reg in ID/EX
    reg [1:0] MemtoReg_DE;
    reg RegWrite_DE;
    reg Branch_DE;
    reg [1:0] MemWrite_DE;
    reg [1:0] MemRead_DE;
    reg ALUSrc_DE;
    reg [1:0] ALUOp_DE;
    reg [1:0] ALUDst_DE;
    reg DMSE_DE; // 0: unsigned, 1: signed loadでしか用いない.
    reg ALUorSHIFT_DE; // 0: ALU, 1: SHIFT VAL_MUXの選択用
    reg [2:0] FT_DE; // 命令フォーマットタイプ

    // EX reg
    wire [31:0] RD_VAL_E;
    reg [31:0] IMM_VAL_SHIFT_E; // immを2bit左シフトした値
    reg [31:0] DATA1_MUX_E; // DATA1_MUXからのデータ
    reg [31:0] DATA2_MUX_E; // DATA2_MUXからのデータ
    reg [31:0] ALU_VAL_E; // ALUからの出力値
    reg [1:0] equalZero_E; // ALUからの出力値
    wire isBranch_E; // 分岐命令かどうかのフラグ
    reg [31:0] WA_E; // 書き込みアドレス
    reg [31:0] WD_E; // 書き込みデータ（WD_D → WD_E）
    reg [31:0] PC_IMM_E; // PC + IMM
    reg [31:0] IMM_VAL_E; // IDから渡されたimm値

    // EX/MEM pipeline reg
    
    reg [31:0] PC_EM;
    reg [31:0] PC4_EM;
    reg [31:0] WA_EM;
    reg [31:0] WD_EM;
    reg [31:0] RD_VAL_EM; // 追加
    reg [4:0] RD_EM;
    reg [2:0] FT_EM; // 命令フォーマットタイプ
    reg [4:0] IALU_EM;

    // Control reg in EX/MEM
    reg [1:0] MemtoReg_EM;
    reg RegWrite_EM;
    reg [1:0] MemWrite_EM;
    reg [1:0] MemRead_EM;
    reg DMSE_EM; // 0: unsigned, 1: signed loadでしか用いない.

    // MEM reg
    reg [31:0] MEM_DATA_M;
    reg [31:0] WA_M;
    reg [31:0] WD_M;

    // MEM/WB pipeline reg
    reg [31:0] PC_MW;
    reg [31:0] PC4_MW;
    reg [31:0] MEM_DATA_MW;
    reg [31:0] WA_MW;
    reg [31:0] RD_VAL_MW; // 追加
    reg [4:0] RD_MW;
    // Control reg in MEM/WB
    reg [1:0] MemtoReg_MW;
    reg RegWrite_MW;

    // WB reg
    reg [31:0] PC4_WB;
    reg [31:0] MEM_DATA_WB;
    reg [31:0] WA_WB;
    reg [31:0] WB_MUX;
 
    // IF stage
    assign PC4_IF = PC_IF + 4;
    
    always @(posedge CLK or posedge RST)
    begin
        if (RST)
            PC_IF <= 32'h00000000;
        else if (isBranch_E)
            PC_IF <= PC_IMM_E;
        else
            PC_IF <= PC4_IF;
    end	

    assign IDATA_IF = imem[PC_IF[31:2]];

    // IF/ID pipeline reg update
    always @(posedge CLK or posedge RST)
    begin
        if (RST)
        begin
            PC_FD <= 32'h00000000;
            PC4_FD <= 32'h00000004;
            IDATA_FD <= 32'h00000000;
        end
        else
        begin
            PC_FD <= PC_IF;
            PC4_FD <= PC4_IF;
            IDATA_FD <= IDATA_IF;
        end
    end

    // define IR
    `ifdef BIG_ENDIAN
    assign IR = IDATA_FD;
    `endif
    `ifdef LITTLE_ENDIAN
    assign IR = {IDATA_FD[7:0], IDATA_FD[15:8], IDATA_FD[23:16], IDATA_FD[31:24]};
    `endif

    // ID stage
    // Instruction decoder
    always @(IR)
    begin
        FT_ID <= 3'b000; // default : undefined instruction
        IALU_ID <= `IADD;  // default operation
        MemtoReg_ID <= 2'b00;  // for R-type(00 for alu), I-type(01 for dmem), U-type(10 for PC+4)
        MemWrite_ID <= 2'b00;  // no store
        MemRead_ID <= 2'b00;  // no load
        DMSE_ID <= 1'b0;   // unsigned
        RS1_PC_ID <= 1'b0;   // no use PC for RS1
        RS1_Z_ID <= 1'b0;   // no use Zero for RS1 
        PC_E_ID <= 1'b0;   // no branch
        
        case(`IR_OP)
            `OP_LUI:
            begin 
                FT_ID <= `FT_U;
                RS1_Z_ID <= 1'b1;
            end
            `OP_AUIPC: 
            begin
                FT_ID <= `FT_U;
                RS1_PC_ID <= 1'b1;
            end
            `OP_JAL:
            begin
                FT_ID <= `FT_J;
                RS1_PC_ID <= 1'b1;
                PC_E_ID <= 1'b1; 
                MemtoReg_ID <= 2'b10;
            end
            `OP_JALR: 
            begin
                FT_ID <= `FT_I;
                PC_E_ID <= 1'b1; 
                MemtoReg_ID <= 2'b10;
            end
            `OP_BR: 
            begin
                FT_ID <= `FT_B;
                PC_E_ID <= 1'b1;
                case(`IR_F3)
                    3'b000: IALU_ID <= `IADD; // beq (仮にIADD、実際は比較演算)
                    3'b001: IALU_ID <= `ISUB; // bne
                    3'b100: IALU_ID <= `ISUB; // blt
                    3'b101: IALU_ID <= `IADD; // bge
                    3'b110: IALU_ID <= `ISUB; // bltu
                    3'b111: IALU_ID <= `IADD; // bgeu
                endcase
            end
            `OP_LOAD:
            begin
                FT_ID <= `FT_I;
                MemtoReg_ID <= 2'b01;
                case(`IR_F3)
                    3'b000: begin MemRead_ID <= 2'b01; DMSE_ID <= 1'b1; end // lb
                    3'b001: begin MemRead_ID <= 2'b10; DMSE_ID <= 1'b1; end // lh
                    3'b010: begin MemRead_ID <= 2'b11; DMSE_ID <= 1'b1; end // lw
                    3'b100: MemRead_ID <= 2'b01; // lbu
                    3'b101: MemRead_ID <= 2'b10; // lhu
                    3'b110: MemRead_ID <= 2'b11; // lwu
                endcase
            end
            `OP_STORE:
            begin
                FT_ID <= `FT_S;
                case(`IR_F3)
                    3'b000: MemWrite_ID <= 2'b01; // sb
                    3'b001: MemWrite_ID <= 2'b10; // sh
                    3'b010: MemWrite_ID <= 2'b11; // sw
                endcase
            end
            `OP_FUNC1: // Immediate
            begin
                FT_ID <= `FT_I;
                case(`IR_F3)
                    3'b000: IALU_ID <= `IADD; // addi
                    3'b001: if(`IR_F7 == 7'b0000000) IALU_ID <= `ISLL; // slli
                    3'b010: IALU_ID <= `IADD; // slti (仮にIADD)
                    3'b011: IALU_ID <= `IADD; // sltiu (仮にIADD)
                    3'b100: IALU_ID <= `IXOR; // xori
                    3'b101: begin
                        if(`IR_F7 == 7'b0000000) IALU_ID <= `ISRL; // srli
                        else if(`IR_F7 == 7'b0100000) IALU_ID <= `ISRA; // srai
                    end
                    3'b110: IALU_ID <= `IOR; // ori
                    3'b111: IALU_ID <= `IAND; // andi
                endcase
            end
            `OP_FUNC2: // R type
            begin
                FT_ID <= `FT_R;
                case(`IR_F3)
                    3'b000: begin
                        if(`IR_F7 == 7'b0000000) IALU_ID <= `IADD; // add
                        else if(`IR_F7 == 7'b0100000) IALU_ID <= `ISUB; // sub
                    end
                    3'b001: if(`IR_F7 == 7'b0000000) IALU_ID <= `ISLL; // sll
                    3'b010: if(`IR_F7 == 7'b0000000) IALU_ID <= `IADD; // slt (仮にIADD)
                    3'b011: if(`IR_F7 == 7'b0000000) IALU_ID <= `IADD; // sltu (仮にIADD)
                    3'b100: if(`IR_F7 == 7'b0000000) IALU_ID <= `IXOR; // xor
                    3'b101: begin
                        if(`IR_F7 == 7'b0000000) IALU_ID <= `ISRL; // srl
                        else if(`IR_F7 == 7'b0100000) IALU_ID <= `ISRA; // sra
                    end
                    3'b110: if(`IR_F7 == 7'b0000000) IALU_ID <= `IOR; // or
                    3'b111: if(`IR_F7 == 7'b0000000) IALU_ID <= `IAND; // and
                endcase
            end
        endcase
        
        RD_ID <= `IR_RD;
    end

    // rf
    rf rf_inst(
        .CLK(CLK),
        .RNUM1(`IR_RS1), .RDATA1(RF_DATA1),
        .RNUM2(`IR_RS2), .RDATA2(RF_DATA2),
        .WNUM(RD_MW),    .WDATA(RD_VAL_MW)
    );

    // ID/EX pipeline reg update
    always @(posedge CLK or posedge RST)
    begin
        if (RST)
        begin
            PC_DE <= 32'h00000000;
            PC4_DE <= 32'h00000000;
            RF_DATA1_DE <= 32'h00000000;
            RF_DATA2_DE <= 32'h00000000;
            IALU_DE <= 5'b00000;
            RD_DE <= 5'b00000;
        end
        else
        begin
            PC_DE <= PC_FD;
            PC4_DE <= PC4_FD;
            RF_DATA1_DE <= RF_DATA1;
            RF_DATA2_DE <= RF_DATA2;
            IALU_DE <= IALU_ID;
            RD_DE <= RD_ID;
        end
    end

    // EX stage
    alu alu_inst(
        .A(RF_DATA1_DE), 
        .B(RF_DATA2_DE), 
        .C(IALU_DE), 
        .Y(RD_VAL_E)
    );

    // EX/MEM pipeline reg update
    always @(posedge CLK or posedge RST)
    begin
        if (RST)
        begin
            PC_EM <= 32'h00000000;
            PC4_EM <= 32'h00000000;
            RD_VAL_EM <= 32'h00000000;
            RD_EM <= 5'b00000;
        end
        else
        begin
            PC_EM <= PC_DE;
            PC4_EM <= PC4_DE;
            RD_VAL_EM <= RD_VAL_E;
            RD_EM <= RD_DE;
        end
    end

    // MEM/WB pipeline reg update
    always @(posedge CLK or posedge RST)
    begin
        if (RST)
        begin
            PC_MW <= 32'h00000000;
            PC4_MW <= 32'h00000000;
            RD_VAL_MW <= 32'h00000000;
            RD_MW <= 5'b00000;
        end
        else
        begin
            PC_MW <= PC_EM;
            PC4_MW <= PC4_EM;
            RD_VAL_MW <= RD_VAL_EM;
            RD_MW <= RD_EM;
        end
    end

    // isBranch_E の定義を追加（仮実装）
    assign isBranch_E = 1'b0; // 実際の分岐判定ロジックを実装する必要がある

    // define output
    always @(posedge CLK)
    begin
        WE_RD_VAL <= RD_VAL_MW;
    end

endmodule

seminor-dir/riscv-np/np/tb.v
`include "riscv.vh"

`timescale 1ns / 1ns

module riscv_tb ();

   reg CLK, RSTN;

`ifdef VCD
   initial
     begin
	// for iverilog + gtkwave and the others
	$dumpfile("riscv.vcd");
	$dumpvars(0, riscv );
     end
`endif
   
   initial
     begin
	CLK = 0;
	while( 1 )
	  CLK = #5 ~CLK;
     end

   //
   // Data Memory Dump for Debug
   //
   task dump;
      input [31:0] addr;

      integer 	   i;
      reg [31:0] data;
      
      for( i = addr ; i<1024 ; i=i+1 )
	begin
     // Data memory hierarchical access is available only on the origin core
`ifdef ORIGIN
     data = riscv.dmem.mem[i];
`else
     // Pipeline core doesn't expose DMEM array; skip or set to X
     data = 32'hXXXXXXXX;
`endif
	   $display( "%08x %02x%02x%02x%02x", addr+i*4,
		     data[7:0], data[15:8], data[23:16], data[31:24] );
	end
   endtask


   initial
     begin
	RSTN = 1;
	RSTN = #10 0;
	RSTN = #10 1;
	#4000000000;
	dump(0);
	$finish();
     end
   
   always @( posedge CLK )
`ifdef ORIGIN
  if( riscv.PC== 32'h00000064 ) // Last instruction address (ebreak) on "startup.s"
`else
  if( riscv.PC_IF== 32'h00000064 ) // Last instruction address (ebreak) on "startup.s"
`endif
       begin
	  $display("Time", $time );
	  dump(0);
	  $finish;	     
       end
   
   riscv #( .IMEM_FILE("prog.mif"),
	    .DMEM_FILE("data.mif"),
	    .IMEM_SIZE(32768),
	    .DMEM_SIZE(32768)
	    )
   riscv ( .CLK(CLK), .RSTN(RSTN) );

   //
   // Debug code
   //
`ifdef ST_DEBUG
   always @( negedge CLK )
`ifdef ORIGIN
  if(  ( riscv.DMWE ) && ( riscv.MADDR[31:20] == 12'h001 ) )
`else
  if( 1'b0 ) // not available on pipeline core
`endif
	 $display( "ST  :%08h %08h %01h ", {riscv.MADDR,2'b00}, riscv.RF_DATA2, riscv.DMWE );
`endif
`ifdef LD_DEBUG
   always @( negedge CLK )
`ifdef ORIGIN
  if(  ( riscv.DMRE  ) && ( riscv.MADDR[31:20] == 12'h001 ) )
    $display( "LD  :%08h %08h %01h ", {riscv.MADDR,2'b00}, riscv.daligner.DATAO, riscv.DMRE );
`else
  if( 1'b0 ) ; // not available on pipeline core
`endif
`endif

endmodule

seminor-dir/riscv-np/np/riscv.vcd
$date
	Mon Oct 27 09:44:32 2025
$end
$version
	Icarus Verilog
$end
$timescale
	1ns
$end
$scope module riscv_tb $end
$scope module riscv $end
$var wire 1 ! CLK $end
$var wire 32 " IDATA_IF [31:0] $end
$var wire 1 # RST $end
$var wire 1 $ RSTN $end
$var wire 1 % isBranch_E $end
$var wire 32 & RF_DATA2 [31:0] $end
$var wire 32 ' RF_DATA1 [31:0] $end
$var wire 32 ( RD_VAL_E [31:0] $end
$var wire 32 ) PC4_IF [31:0] $end
$var wire 32 * IR [31:0] $end
$var reg 1 + DMSE_ID $end
$var reg 3 , FT_ID [2:0] $end
$var reg 5 - IALU_DE [4:0] $end
$var reg 5 . IALU_ID [4:0] $end
$var reg 32 / IDATA_FD [31:0] $end
$var reg 2 0 MemRead_ID [1:0] $end
$var reg 2 1 MemWrite_ID [1:0] $end
$var reg 2 2 MemtoReg_ID [1:0] $end
$var reg 32 3 PC4_DE [31:0] $end
$var reg 32 4 PC4_EM [31:0] $end
$var reg 32 5 PC4_FD [31:0] $end
$var reg 32 6 PC4_MW [31:0] $end
$var reg 32 7 PC_DE [31:0] $end
$var reg 32 8 PC_EM [31:0] $end
$var reg 1 9 PC_E_ID $end
$var reg 32 : PC_FD [31:0] $end
$var reg 32 ; PC_IF [31:0] $end
$var reg 32 < PC_IMM_E [31:0] $end
$var reg 32 = PC_MW [31:0] $end
$var reg 5 > RD_DE [4:0] $end
$var reg 5 ? RD_EM [4:0] $end
$var reg 5 @ RD_ID [4:0] $end
$var reg 5 A RD_MW [4:0] $end
$var reg 32 B RD_VAL_EM [31:0] $end
$var reg 32 C RD_VAL_MW [31:0] $end
$var reg 32 D RF_DATA1_DE [31:0] $end
$var reg 32 E RF_DATA2_DE [31:0] $end
$var reg 1 F RS1_PC_ID $end
$var reg 1 G RS1_Z_ID $end
$var reg 32 H WE_RD_VAL [31:0] $end
$scope module alu_inst $end
$var wire 32 I A [31:0] $end
$var wire 32 J B [31:0] $end
$var wire 5 K C [4:0] $end
$var wire 1 L overflowFlag $end
$var wire 1 M zeroFlag $end
$var wire 1 N lessThanUnsignedFlag $end
$var wire 1 O lessThanFlag $end
$var reg 33 P X [32:0] $end
$var reg 32 Q Y [31:0] $end
$upscope $end
$scope module rf_inst $end
$var wire 1 ! CLK $end
$var wire 5 R RNUM1 [4:0] $end
$var wire 5 S RNUM2 [4:0] $end
$var wire 32 T WDATA [31:0] $end
$var wire 5 U WNUM [4:0] $end
$var reg 32 V RDATA1 [31:0] $end
$var reg 32 W RDATA2 [31:0] $end
$upscope $end
$upscope $end
$upscope $end
$enddefinitions $end
#0
$dumpvars
bx W
bx V
bx U
bx T
bx S
bx R
bx Q
bx P
xO
xN
xM
xL
bx K
bx J
bx I
bx H
xG
xF
bx E
bx D
bx C
bx B
bx A
bx @
bx ?
bx >
bx =
bx <
bx ;
bx :
x9
bx 8
bx 7
bx 6
bx 5
bx 4
bx 3
bx 2
bx 1
bx 0
bx /
bx .
bx -
bx ,
x+
bx *
bx )
bx (
bx '
bx &
0%
1$
0#
bx "
0!
$end
#5
1!
#10
b0 (
b0 Q
1M
b0 @
09
0G
0F
0+
b0 0
b0 1
b0 2
b0 .
b0 ,
b0 P
0L
b0 S
b0 R
b0 *
b10010011000000000000000000000000 "
b0 A
b0 U
b0 C
b0 T
b0 6
b0 =
b0 ?
b0 B
b0 4
b0 8
b0 >
b0 -
b0 K
0N
0O
b0 E
b0 J
b0 D
b0 I
b0 3
b0 7
b0 /
b100 5
b0 :
b100 )
b0 ;
1#
0!
0$
#15
b0 H
1!
#20
b0 &
b0 W
b0 '
b0 V
0#
0!
1$
#25
b1 @
b10 ,
b10010011 *
b10011000000010000000000000000 "
b100 3
b10010011000000000000000000000000 /
b1000 )
b100 ;
1!
#30
0!
#35
b10 @
b10 ,
b10010011000000010001000000000000 "
b100010011 *
b1100 )
b1000 ;
b10011000000010000000000000000 /
b1000 5
b100 :
b1 >
b100 4
1!
#40
0!
#45
b11 @
b10 ,
b1 S
b100000000000110010011 *
b10011000000100000000000000000 "
b100 6
b1 ?
b10 >
b1000 3
b100 7
b10010011000000010001000000000000 /
b1100 5
b1000 :
b10000 )
b1100 ;
1!
#50
bx &
bx W
0!
#55
bx (
bx Q
xL
xM
b100 @
b10 ,
bx P
b0 S
b10010011000000100000000000000000 "
b1000010011 *
b10100 )
b10000 ;
b10011000000100000000000000000 /
b10000 5
b1100 :
b11 >
xN
xO
bx E
bx J
b1100 3
b1000 7
b10 ?
b1000 4
b100 8
b1 A
b1 U
1!
#60
b0 &
b0 W
0!
#65
b0 (
b0 Q
1M
b101 @
b10 ,
b0 P
0L
b1010010011 *
b10011000000110000000000000000 "
b10 A
b10 U
b1000 6
b100 =
b11 ?
bx B
b1100 4
b1000 8
b100 >
0N
0O
b0 E
b0 J
b10000 3
b1100 7
b10010011000000100000000000000000 /
b10100 5
b10000 :
b11000 )
b10100 ;
1!
#70
0!
#75
b110 @
b10 ,
b10010011000000110000000000000000 "
b1100010011 *
b11100 )
b11000 ;
b10011000000110000000000000000 /
b11000 5
b10100 :
b101 >
b10100 3
b10000 7
b100 ?
b0 B
b10000 4
b1100 8
b11 A
b11 U
bx C
bx T
b1100 6
b1000 =
1!
#80
0!
#85
b111 @
b10 ,
b1110010011 *
b10011000001000000000000000000 "
bx H
b100 A
b100 U
b0 C
b0 T
b10000 6
b1100 =
b101 ?
b10100 4
b10000 8
b110 >
b11000 3
b10100 7
b10010011000000110000000000000000 /
b11100 5
b11000 :
b100000 )
b11100 ;
1!
#90
0!
#95
b1000 @
b10 ,
b10010011000001000000000000000000 "
b10000010011 *
b0 H
b100100 )
b100000 ;
b10011000001000000000000000000 /
b100000 5
b11100 :
b111 >
b11100 3
b11000 7
b110 ?
b11000 4
b10100 8
b101 A
b101 U
b10100 6
b10000 =
1!
#100
0!
#105
b1001 @
b10 ,
b10010010011 *
b10011000001010000000000000000 "
b110 A
b110 U
b11000 6
b10100 =
b111 ?
b11100 4
b11000 8
b1000 >
b100000 3
b11100 7
b10010011000001000000000000000000 /
b100100 5
b100000 :
b101000 )
b100100 ;
1!
#110
0!
#115
b1010 @
b10 ,
b10010011000001010000000000000000 "
b10100010011 *
b101100 )
b101000 ;
b10011000001010000000000000000 /
b101000 5
b100100 :
b1001 >
b100100 3
b100000 7
b1000 ?
b100000 4
b11100 8
b111 A
b111 U
b11100 6
b11000 =
1!
#120
0!
#125
b1011 @
b10 ,
b10110010011 *
b10011000001100000000000000000 "
b1000 A
b1000 U
b100000 6
b11100 =
b1001 ?
b100100 4
b100000 8
b1010 >
b101000 3
b100100 7
b10010011000001010000000000000000 /
b101100 5
b101000 :
b110000 )
b101100 ;
1!
#130
0!
#135
b1100 @
b10 ,
b10010011000001100000000000000000 "
b11000010011 *
b110100 )
b110000 ;
b10011000001100000000000000000 /
b110000 5
b101100 :
b1011 >
b101100 3
b101000 7
b1010 ?
b101000 4
b100100 8
b1001 A
b1001 U
b100100 6
b100000 =
1!
#140
0!
#145
b1101 @
b10 ,
b11010010011 *
b10011000001110000000000000000 "
b1010 A
b1010 U
b101000 6
b100100 =
b1011 ?
b101100 4
b101000 8
b1100 >
b110000 3
b101100 7
b10010011000001100000000000000000 /
b110100 5
b110000 :
b111000 )
b110100 ;
1!
#150
0!
#155
b1110 @
b10 ,
b10010011000001110000000000000000 "
b11100010011 *
b111100 )
b111000 ;
b10011000001110000000000000000 /
b111000 5
b110100 :
b1101 >
b110100 3
b110000 7
b1100 ?
b110000 4
b101100 8
b1011 A
b1011 U
b101100 6
b101000 =
1!
#160
0!
#165
b1111 @
b10 ,
b11110010011 *
b10010111000100010001000000000000 "
b1100 A
b1100 U
b110000 6
b101100 =
b1101 ?
b110100 4
b110000 8
b1110 >
b111000 3
b110100 7
b10010011000001110000000000000000 /
b111100 5
b111000 :
b1000000 )
b111100 ;
1!
#170
0!
#175
b11 @
1F
b100 ,
b1 S
b10010011100000010100000101111100 "
b100000001000110010111 *
b1000100 )
b1000000 ;
b10010111000100010001000000000000 /
b1000000 5
b111100 :
b1111 >
b111100 3
b111000 7
b1110 ?
b111000 4
b110100 8
b1101 A
b1101 U
b110100 6
b110000 =
1!
#180
0!
#185
0F
b10 ,
b100 S
b11 R
b1111100010000011000000110010011 *
b10111001000010001000000000000 "
b1110 A
b1110 U
b111000 6
b110100 =
b1111 ?
b111100 4
b111000 8
b11 >
b1000000 3
b111100 7
b10010011100000010100000101111100 /
b1000100 5
b1000000 :
b1001000 )
b1000100 ;
1!
#190
bx '
bx V
0!
#195
bx (
bx Q
xM
b10 @
1F
b100 ,
bx P
xL
b1 S
b0 R
b10011000000011100000111111011 "
b100000010000100010111 *
b1001100 )
b1001000 ;
b10111001000010001000000000000 /
b1001000 5
b1000100 :
xN
xO
bx D
bx I
b1000100 3
b1000000 7
b11 ?
b1000000 4
b111100 8
b1111 A
b1111 U
b111100 6
b111000 =
1!
#200
b0 '
b0 V
0!
#205
b0 (
b0 Q
1M
0F
b10 ,
b0 P
0L
b10 R
b11100 S
b11111011110000010000000100010011 *
b10011000001010000000000000000 "
b11 A
b11 U
b1000000 6
b111100 =
bx B
b1000100 4
b1000000 8
b10 >
0N
0O
b0 D
b0 I
b1001000 3
b1000100 7
b10011000000011100000111111011 /
b1001100 5
b1001000 :
b1010000 )
b1001100 ;
1!
#210
bx &
bx W
0!
#215
bx (
bx Q
xL
xM
b1010 @
b10 ,
bx P
b0 R
b0 S
b10010011000001010000000000000000 "
b10100010011 *
b1010100 )
b1010000 ;
b10011000001010000000000000000 /
b1010000 5
b1001100 :
xN
xO
bx E
bx J
b1001100 3
b1001000 7
b10 ?
b0 B
b1001000 4
b1000100 8
bx C
bx T
b1000100 6
b1000000 =
1!
#220
b0 &
b0 W
0!
